AUTHORS.rst
CONTRIBUTING.rst
HISTORY.rst
LICENSE
MANIFEST.in
README.rst
setup.cfg
setup.py
bin/dgit
dgitcore/__init__.py
dgitcore/api.py
dgitcore/config.py
dgitcore/exceptions.py
dgitcore/helper.py
dgitcore/contrib/backends/local.py
dgitcore/contrib/backends/s3.py
dgitcore/contrib/instrumentations/content.py
dgitcore/contrib/instrumentations/executable.py
dgitcore/contrib/instrumentations/platform.py
dgitcore/contrib/metadata/default.py
dgitcore/contrib/repomanagers/gitmanager.py
dgitcore/contrib/representations/tableformat.py
dgitcore/contrib/validators/metadata_validator.py
dgitcore/contrib/validators/regression_quality.py
dgitcore/datasets/__init__.py
dgitcore/datasets/auto.py
dgitcore/datasets/common.py
dgitcore/datasets/files.py
dgitcore/datasets/history.py
dgitcore/datasets/transformation.py
dgitcore/datasets/validation.py
dgitcore/plugins/__init__.py
dgitcore/plugins/backend.py
dgitcore/plugins/common.py
dgitcore/plugins/instrumentation.py
dgitcore/plugins/metadata.py
dgitcore/plugins/repomanager.py
dgitcore/plugins/representation.py
dgitcore/plugins/transformer.py
dgitcore/plugins/validator.py
dgitcore/vendor/pluginbase/pluginbase.py
docs/Makefile
docs/README.rst
docs/api.rst
docs/auto.rst
docs/code.rst
docs/conf.py
docs/config.rst
docs/faq.rst
docs/index.rst
tests/__init__.py
tests/test_api.py
tests/test_cli.py
tests/assets/dgit-api.ini
tests/assets/dgit-cli.ini