Metadata-Version: 1.1
Name: dgit
Version: 0.1.7
Summary: Git wrapper for Managing Datasets
Home-page: https://github.com/pingali/dgit
Author: Venkata Pingali
Author-email: pingali@gmail.com
License: MIT
Keywords: git data datasets versioning cvs
Platform: UNKNOWN
Classifier: Development Status :: 3 - Alpha
Classifier: Intended Audience :: Developers
Classifier: Natural Language :: English
Classifier: License :: OSI Approved :: MIT License
Classifier: Programming Language :: Python :: 3 :: Only
Classifier: Topic :: Scientific/Engineering :: Information Analysis
